kitconcept/__init__.py
kitconcept/intranet/__init__.py
kitconcept/intranet/_types.py
kitconcept/intranet/configure.zcml
kitconcept/intranet/dependencies.zcml
kitconcept/intranet/distributions.zcml
kitconcept/intranet/handlers.py
kitconcept/intranet/interfaces.py
kitconcept/intranet/overrides.zcml
kitconcept/intranet/permissions.zcml
kitconcept/intranet/profiles.zcml
kitconcept/intranet/search.py
kitconcept/intranet/behaviors/__init__.py
kitconcept/intranet/behaviors/clm.py
kitconcept/intranet/behaviors/configure.zcml
kitconcept/intranet/behaviors/location.py
kitconcept/intranet/behaviors/organisational_unit.py
kitconcept/intranet/behaviors/person.py
kitconcept/intranet/behaviors/votes.py
kitconcept/intranet/content/location.py
kitconcept/intranet/content/organisational_unit.py
kitconcept/intranet/controlpanels/__init__.py
kitconcept/intranet/controlpanels/configure.zcml
kitconcept/intranet/controlpanels/intranet.py
kitconcept/intranet/distributions/intranet/image.png
kitconcept/intranet/distributions/intranet/profiles.json
kitconcept/intranet/distributions/intranet/schema.json
kitconcept/intranet/distributions/intranet/content/.gitignore
kitconcept/intranet/distributions/intranet/content/discussions.json
kitconcept/intranet/distributions/intranet/content/portlets.json
kitconcept/intranet/distributions/intranet/content/principals.json
kitconcept/intranet/distributions/intranet/content/redirects.json
kitconcept/intranet/distributions/intranet/content/relations.json
kitconcept/intranet/distributions/intranet/content/translations.json
kitconcept/intranet/distributions/intranet/content/content/__metadata__.json
kitconcept/intranet/distributions/intranet/content/content/00cef5f245a342958288ace545e3c097/data.json
kitconcept/intranet/distributions/intranet/content/content/01adf6c29d8d4fbda102aabf7f9391de/data.json
kitconcept/intranet/distributions/intranet/content/content/0231e377bff44d4a89d4508378f073d9/data.json
kitconcept_intranet-2.0.0a5.dist-info/METADATA
kitconcept_intranet-2.0.0a5.dist-info/WHEEL
kitconcept_intranet-2.0.0a5.dist-info/entry_points.txt
kitconcept_intranet-2.0.0a5.dist-info/licenses/LICENSE.GPL
kitconcept_intranet-2.0.0a5.dist-info/licenses/LICENSE.md
kitconcept_intranet-2.0.0a5.dist-info/RECORD
