Metadata-Version: 2.4
Name: kitconcept.intranet
Version: 2.0.0a5
Summary: A Plone distribution for Intranets with Plone. Created by kitconcept.
Project-URL: Homepage, https://github.com/kitconcept/kitconcept.intranet
Project-URL: PyPI, https://pypi.python.org/pypi/kitconcept.intranet
Project-URL: Source, https://github.com/kitconcept/kitconcept.intranet
Project-URL: Tracker, https://github.com/kitconcept/kitconcept.intranet/issues
Author-email: kitconcept GmbH <info@kitconcept.com>
License-Expression: MIT
License-File: LICENSE.GPL
License-File: LICENSE.md
Keywords: CMS,Intranet,Plone,Python
Classifier: Development Status :: 3 - Alpha
Classifier: Environment :: Web Environment
Classifier: Framework :: Plone
Classifier: Framework :: Plone :: 6.1
Classifier: Framework :: Plone :: Distribution
Classifier: License :: OSI Approved :: GNU General Public License v2 (GPLv2)
Classifier: Operating System :: OS Independent
Classifier: Programming Language :: Python
Classifier: Programming Language :: Python :: 3.12
Requires-Python: ==3.12.*
Requires-Dist: collective-solr==10.0.0
Requires-Dist: kitconcept-core==2.0.0a8
Requires-Dist: kitconcept-solr==2.0.0a8
Requires-Dist: pas-plugins-authomatic==2.0.0
Requires-Dist: pas-plugins-keycloakgroups==1.0.0b1
Requires-Dist: pas-plugins-oidc==2.0.0
Requires-Dist: plone-api
Requires-Dist: plone-app-discussion
Requires-Dist: plone-app-querystring>=3.0.0a2
Requires-Dist: plone-distribution
Requires-Dist: plone-restapi
Requires-Dist: plone-volto>=5.1.0
Requires-Dist: python-dateutil
Requires-Dist: redturtle-rssservice==2.2.0
